[
    {
        "name" : "Jimbu Thakali Thali (Chicken)" ,
        "description" : "locally grown rice with dal imported from lower regions to the south ,vegetables,ghee with chicken curry",
        "price" : "650",
        "imagePath" : ""
    },
    {
        "name" : "Jimbu Thakali Thali (Mutton)",
        "description" : "locally grown rice with dal imported from lower regions to the south ,vegetables,ghee with mutton(goat) curry",
        "price" : "750",
        "imagePath" : ""
    },
    {
        "name" : "Jimbu Thakali Thali (Fish)" ,
        "description" : "locally grown rice with dal imported from lower regions to the south ,vegetables,ghee with fish curry" ,
        "price" : "600" ,
        "imagePath" : "" 
    },
    {
        "name" : "Jimbu Thakali Thali (Veg.)" ,
        "description" : "locally grown rice with dal imported from lower regions to the south ,vegetables & ghee" ,
        "price" : "500" ,
        "imagePath" : ""
    },
    {
        "name" : "Dhido Thali (Chicken)" ,
        "description" : "dish prepared by gradually adding flour to boiling water while stirring served with different vegetables and chicken curry." ,
        "price" : "600" ,
        "imagePath" : ""
    },
    {
        "name" : "Dhido Thali (Mutton)" ,
        "description" : "dish prepared by gradually adding flour to boiling water while stirring served with different vegetables and mutton(goat) curry." ,
        "price" : "770" ,
        "imagePath" : ""
    },
    {
        "name" : "Dhido Thali (Veg.)" ,
        "description" : "dish prepared by gradually adding flour to boiling water while stirring served with different vegetables." ,
        "price" : "500" ,
        "imagePath" : ""
    },
    {
        "name" : "Royal Briyani" ,
        "description" : "mixed rice dish originating among the Muslims of the Indian subcontinent as a variety of Persian pilaf. It is made with Indian spices, rice and meat.",
        "price" : "1500" ,
        "imagePath" : ""
    },
    {
        "name" : "Tandoori duo Chicken n Lamb" ,
        "description" : "fusion of tandoori specialties: chicken tikka, lamb tikka, chicken seekh kabob, lamb seekh kabob, tandoori chicken" ,
        "price" : "2100",
        "imagePath" : ""
    }
]